asdoc2dash
