Metadata-Version: 1.1
Name: asdoc2dash
Version: 0.1.1
Summary: asdoc2dash is tools that convert from ASDoc to Dash Docset.
Home-page: https://github.com/ton1517/asdoc2dash
Author: ton1517
Author-email: tonton1517@gmail.com
License: MIT License
Platform: any
Classifier: Development Status :: 3 - Alpha
Classifier: Environment :: Console
Classifier: Intended Audience :: Developers
Classifier: License :: OSI Approved :: MIT License
Classifier: Operating System :: MacOS :: MacOS X
Classifier: Topic :: Documentation
Classifier: Topic :: Software Development
Classifier: Topic :: Software Development :: Documentation
Classifier: Topic :: Text Processing
